iMapHub/GlobalToLocal.py
iMapHub/__init__.py
iMapHub-1.0.0.dist-info/LICENSE
iMapHub-1.0.0.dist-info/METADATA
iMapHub-1.0.0.dist-info/WHEEL
iMapHub-1.0.0.dist-info/top_level.txt
iMapHub-1.0.0.dist-info/RECORD
