Metadata-Version: 2.1
Name: iMapHub
Version: 1.0.0
Summary: Library created to map two Dataset
Home-page: UNKNOWN
Author: iMapHub
Author-email: iMap.Hub@unilever.com
License: UNKNOWN
Platform: UNKNOWN
Classifier: Programming Language :: Python :: 3
Classifier: License :: OSI Approved :: MIT License
Classifier: Operating System :: OS Independent
Requires-Python: >=3.7
License-File: LICENSE
Requires-Dist: pyspark
Requires-Dist: spark
Requires-Dist: pandas
Requires-Dist: databricks-sdk
